odoo/addons/l10n_fr_department_oversea/README.rst
odoo/addons/l10n_fr_department_oversea/__init__.py
odoo/addons/l10n_fr_department_oversea/__manifest__.py
odoo/addons/l10n_fr_department_oversea/post_install.py
odoo/addons/l10n_fr_department_oversea/pre_init_hook.py
odoo/addons/l10n_fr_department_oversea/data/res_country_department.xml
odoo/addons/l10n_fr_department_oversea/data/res_country_state.xml
odoo/addons/l10n_fr_department_oversea/readme/CONTRIBUTORS.md
odoo/addons/l10n_fr_department_oversea/readme/DESCRIPTION.md
odoo/addons/l10n_fr_department_oversea/static/description/icon.png
odoo/addons/l10n_fr_department_oversea/static/description/index.html
odoo/addons/l10n_fr_department_oversea/tests/__init__.py
odoo/addons/l10n_fr_department_oversea/tests/test_department_oversea.py
odoo_addon_l10n_fr_department_oversea-19.0.1.0.0.2.dist-info/METADATA
odoo_addon_l10n_fr_department_oversea-19.0.1.0.0.2.dist-info/WHEEL
odoo_addon_l10n_fr_department_oversea-19.0.1.0.0.2.dist-info/top_level.txt
odoo_addon_l10n_fr_department_oversea-19.0.1.0.0.2.dist-info/RECORD
