Metadata-Version: 2.1
Name: odoo-addon-l10n_fr_department_oversea
Version: 19.0.1.0.0.2
Requires-Dist: odoo-addon-l10n_fr_department==19.0.*
Requires-Dist: odoo==19.0.*
Summary: =?utf-8?q?Populate_Database_with_overseas_French_Departments_=28D=C3=A9partements_d=27outre-mer=29?=
Home-page: https://github.com/OCA/l10n-france
License: AGPL-3
Author: Akretion,Odoo Community Association (OCA)
Author-email: support@odoo-community.org
Classifier: Programming Language :: Python
Classifier: Framework :: Odoo
Classifier: Framework :: Odoo :: 19.0
Classifier: License :: OSI Approved :: GNU Affero General Public License v3
